travdata/__init__.py
travdata/cli/__init__.py
travdata/cli/cli.py
travdata/cli/cliutil.py
travdata/cli/cmds/__init__.py
travdata/cli/cmds/extractcsvtables.py
travdata/cli/cmds/licenses.py
travdata/cli/cmds/listbooks.py
travdata/cli/cmds/tradetable.py
travdata/commontext.py
travdata/config/__init__.py
travdata/config/cfgerror.py
travdata/config/cfgextract.py
travdata/config/yamlreg.py
travdata/csvutil.py
travdata/dataclassutil.py
travdata/datatypes/__init__.py
travdata/datatypes/basic.py
travdata/datatypes/core/__init__.py
travdata/datatypes/core/trade.py
travdata/datatypes/core/worldcreation.py
travdata/extraction/__init__.py
travdata/extraction/bookextract.py
travdata/extraction/ecmastransform.py
travdata/extraction/index.py
travdata/extraction/parseutil.py
travdata/extraction/pdf/__init__.py
travdata/extraction/pdf/cachingreader.py
travdata/extraction/pdf/tablereader.py
travdata/extraction/pdf/tabulareader.py
travdata/extraction/tableextract.py
travdata/extraction/transforms.py
travdata/filesio.py
travdata/gui/__init__.py
travdata/gui/extraction/__init__.py
travdata/gui/extraction/cfgwin.py
travdata/gui/extraction/runnerwin.py
travdata/gui/gui.py
travdata/gui/qtutil.py
travdata/py.typed
travdata/tableconverters/__init__.py
travdata/tableconverters/core/__init__.py
travdata/tableconverters/core/registry.py
travdata/tableconverters/core/trade.py
travdata/tableconverters/core/worldcreation.py
travdata/tableconverters/registry.py
travdata/tabledata.py
travdata/travdatarelease.py
travdata/travellermap/__init__.py
travdata/travellermap/apiurls.py
travdata/travellermap/sectorparse.py
travdata/travellermap/world.py
travdata/yamlutil.py
travdata-0.6.2.dist-info/LICENSE
travdata-0.6.2.dist-info/METADATA
travdata-0.6.2.dist-info/WHEEL
travdata-0.6.2.dist-info/entry_points.txt
travdata-0.6.2.dist-info/RECORD
