Metadata-Version: 2.1
Name: travdata
Version: 0.6.2
Summary: Data utility code for Mongoose Traveller TTRPG.
Home-page: https://github.com/huin/travdata
License: MIT
Keywords: traveller,ttrpg
Author: John Beisley
Author-email: johnbeisleyuk@gmail.com
Requires-Python: >=3.11,<4.0
Classifier: License :: OSI Approved :: MIT License
Classifier: Programming Language :: Python :: 3
Classifier: Programming Language :: Python :: 3.11
Classifier: Programming Language :: Python :: 3.12
Requires-Dist: cachetools (>=5.3.3,<6.0.0)
Requires-Dist: jpype1 (>=1.5.0,<2.0.0)
Requires-Dist: pip-licenses-lib (>=0.2.1,<0.3.0)
Requires-Dist: progress (>=1.6,<2.0)
Requires-Dist: pyside6-essentials (>=6.6.3,<7.0.0) ; python_version >= "3.11" and python_version < "3.13"
Requires-Dist: ruamel-yaml (>=0.18.6,<0.19.0)
Requires-Dist: stpyv8 (>=12.6.228.21,<13.0.0.0)
Requires-Dist: tabula-py[jpype] (>=2.9.0,<3.0.0)
Requires-Dist: types-cachetools (>=5.3.0.7,<6.0.0.0)
Requires-Dist: xdg-base-dirs (>=6.0.1,<7.0.0)
Project-URL: Issues, https://github.com/huin/travdata/issues
Project-URL: Repository, https://github.com/huin/travdata
